social_auth_app_django_mongoengine-1.0.0.dist-info/DESCRIPTION.rst
social_auth_app_django_mongoengine-1.0.0.dist-info/METADATA
social_auth_app_django_mongoengine-1.0.0.dist-info/RECORD
social_auth_app_django_mongoengine-1.0.0.dist-info/WHEEL
social_auth_app_django_mongoengine-1.0.0.dist-info/metadata.json
social_auth_app_django_mongoengine-1.0.0.dist-info/top_level.txt
social_django_mongoengine/__init__.py
social_django_mongoengine/config.py
social_django_mongoengine/models.py
