Metadata-Version: 1.1
Name: social-auth-app-django-mongoengine
Version: 1.0.0
Summary: Python Social Authentication, Mongoengine Django integration.
Home-page: https://github.com/python-social-auth/social-app-django-mongoengine
Author: Matias Aguirre
Author-email: matiasaguirre@gmail.com
License: BSD
Keywords: django,social auth,mongoengine
Platform: UNKNOWN
Classifier: Development Status :: 4 - Beta
Classifier: Topic :: Internet
Classifier: License :: OSI Approved :: BSD License
Classifier: Intended Audience :: Developers
Classifier: Environment :: Web Environment
Classifier: Programming Language :: Python
Classifier: Programming Language :: Python :: 2.7
Classifier: Programming Language :: Python :: 3
